promptoria/__init__.py
promptoria/pyprompt.py
pyprompt/__init__.py
pyprompt/pyprompt.py
promptoria-0.1.1.dist-info/LICENSE
promptoria-0.1.1.dist-info/METADATA
promptoria-0.1.1.dist-info/WHEEL
promptoria-0.1.1.dist-info/top_level.txt
promptoria-0.1.1.dist-info/RECORD
